{
  "date": "2026-04-03",
  "prepared_at": "2026-04-03T14:48:08Z",
  "status": "PENDING",
  "today_posts": {
    "count": 5,
    "latest": "With a little more time, we can easily OPEN THE HORMUZ STRAIT, TAKE THE OIL, & MAKE A FORTUNE. IT WOULD BE A \"GUSHER\" FOR THE WORLD??? President DONALD J. TRUMP",
    "earliest_time": "2026-04-03T01:21:34.616Z",
    "latest_time": "2026-04-03T12:22:58.971Z",
    "sample": [
      {
        "time": "01:21",
        "text": "Is Bruce Springsteen going to sue his plastic surgeon?"
      },
      {
        "time": "02:41",
        "text": "Our Military, the greatest and most powerful (by far!) anywhere in the World, hasn't even started destroying what's left in Iran. Bridges next, then Electric Power Plants! New Regime leadership knows what has to be done, and has to be done, FAST! President DONALD J.TRUMP"
      },
      {
        "time": "08:05",
        "text": "Vice President JD Vance is now in charge of вҖңFRAUDвҖқ in the United States. It is massive and pervasive, and the job he will be doing, in conjunction with many great people within the Trump Administration, will be a major factor in how great the future of our Country will be. We will call him the вҖңFRA"
      },
      {
        "time": "12:05",
        "text": "Vice President JD Vance is now in charge of \"FRAUD\" in the United States. It is massive and pervasive, and the job he will be doing, in conjunction with many great people within the Trump Administration, will be a major factor in how great the future of our Country will be. We will call him the \"FRA"
      },
      {
        "time": "12:22",
        "text": "With a little more time, we can easily OPEN THE HORMUZ STRAIT, TAKE THE OIL, & MAKE A FORTUNE. IT WOULD BE A \"GUSHER\" FOR THE WORLD??? President DONALD J. TRUMP"
      }
    ]
  },
  "keyword_signals": [
    "IRAN"
  ],
  "today_features": {
    "posts_1_5": true,
    "avg_len_long": true,
    "caps_high": true,
    "excl_normal": true,
    "questions_yes": true,
    "mostly_premarket": true,
    "has_night": true,
    "kw_iran": true,
    "kw_oil": true,
    "pre_oil": true,
    "kw_great": true,
    "kw_great_2plus": true,
    "pre_great": true,
    "kw_vance": true,
    "kw_vance_2plus": true,
    "pre_vance": true,
    "is_friday": true,
    "volume_rising_3d": true
  },
  "model_performance": {
    "A1_tariff_bearish": {
      "name": "зӣӨдёӯй—ңзЁ…вҶ’йҡ”еӨ©и·Ң",
      "win_rate": 56.5,
      "avg_return": -0.758,
      "total_trades": 23
    },
    "A2_deal_bullish": {
      "name": "DEAL еҮәзҸҫвҶ’йҡ”еӨ©жјІ",
      "win_rate": 52.2,
      "avg_return": 0.029,
      "total_trades": 90
    },
    "A3_relief_rocket": {
      "name": "зӣӨеүҚ RELIEFвҶ’з•¶еӨ©йЈҶ",
      "win_rate": 72.7,
      "avg_return": 1.206,
      "total_trades": 11
    },
    "B1_triple_signal": {
      "name": "дёүдҝЎиҷҹйҪҠзҷјвҶ’иІ·3еӨ©",
      "win_rate": 64.7,
      "avg_return": 0.597,
      "total_trades": 17
    },
    "B2_tariff_to_deal": {
      "name": "йҖЈ3еӨ©й—ңзЁ…вҶ’еҮәзҸҫDealвҶ’иҪүжҠҳ",
      "win_rate": 57.9,
      "avg_return": 0.721,
      "total_trades": 19
    },
    "B3_action_pre": {
      "name": "зӣӨеүҚ ACTION+жӯЈйқўжғ…з·’вҶ’жјІ",
      "win_rate": 66.7,
      "avg_return": 0.199,
      "total_trades": 33
    },
    "C1_burst_silence": {
      "name": "иҪҹзӮёвҶ’й•·жІүй»ҳвҶ’еҒҡеӨҡ",
      "win_rate": 65.3,
      "avg_return": 0.145,
      "total_trades": 176
    },
    "C2_brag_top": {
      "name": "зӮ«иҖҖиӮЎеёӮвҶ’зҹӯжңҹеҲ°й Ӯ",
      "win_rate": 45.0,
      "avg_return": 0.105,
      "total_trades": 60
    },
    "C3_night_alert": {
      "name": "ж·ұеӨңй—ңзЁ…жҺЁж–ҮвҶ’й–ӢзӣӨи·із©ә",
      "win_rate": 37.5,
      "avg_return": -0.414,
      "total_trades": 8
    },
    "D2_sig_change": {
      "name": "з°ҪеҗҚеҲҮжҸӣвҶ’жӯЈејҸиҒІжҳҺ",
      "win_rate": 70.0,
      "avg_return": 0.472,
      "total_trades": 80
    },
    "D3_volume_spike": {
      "name": "зҷјж–ҮйҮҸжҡҙеўһвҶ’жҒҗж…Ңеә•йғЁ",
      "win_rate": 70.2,
      "avg_return": 0.306,
      "total_trades": 47
    }
  },
  "recent_wrong": [
    {
      "model": "C1_burst_silence",
      "date": "2026-03-05",
      "direction": "LONG",
      "actual_return": -1.621
    },
    {
      "model": "A2_deal_bullish",
      "date": "2026-03-10",
      "direction": "LONG",
      "actual_return": -0.305
    },
    {
      "model": "C1_burst_silence",
      "date": "2026-03-11",
      "direction": "LONG",
      "actual_return": -1.73
    },
    {
      "model": "A2_deal_bullish",
      "date": "2026-03-13",
      "direction": "LONG",
      "actual_return": -0.619
    },
    {
      "model": "C1_burst_silence",
      "date": "2026-03-13",
      "direction": "LONG",
      "actual_return": -0.619
    }
  ],
  "learning_summary": {
    "promoted": 4,
    "demoted": 1,
    "eliminated": 1,
    "signal_adjusted": 0
  },
  "evolution_latest": {
    "date": "2026-04-03",
    "crossover": 16,
    "mutation": 11,
    "distill": 16,
    "total_new": 43,
    "total_rules_after": 600,
    "top_3": [
      {
        "features": [
          "kw_corrupt",
          "kw_dow_2plus",
          "kw_tariff"
        ],
        "direction": "LONG",
        "hold": 3,
        "score": 87.5,
        "origin": "crossover"
      },
      {
        "features": [
          "open_tariff",
          "open_thank_you_for_your_attention",
          "kw_tariffs_2plus"
        ],
        "direction": "LONG",
        "hold": 3,
        "score": 87.5,
        "origin": "crossover"
      },
      {
        "features": [
          "kw_dow_2plus",
          "open_deal",
          "kw_jobs"
        ],
        "direction": "LONG",
        "hold": 3,
        "score": 83.3,
        "origin": "crossover"
      }
    ]
  },
  "signal_confidence": {
    "TARIFF": 0.7,
    "DEAL": 0.55,
    "RELIEF": 0.95,
    "ACTION": 0.95,
    "THREAT": 0.6,
    "CHINA": 0.6,
    "IRAN": 0.55,
    "TARIFF_ONLY": 0.7,
    "DEAL_ONLY": 0.65
  },
  "prediction_market": {
    "date": "2026-04-03",
    "signals": [
      "IRAN"
    ],
    "opportunities": [],
    "total_scanned": 0
  }
}